{
  "states": [
    { "name": "Alabama", "abbr": "AL", "slug": "alabama", "medicaidExpanded": false, "exchange": "Healthcare.gov", "ownExchange": false },
    { "name": "Alaska", "abbr": "AK", "slug": "alaska", "medicaidExpanded": true, "exchange": "Healthcare.gov", "ownExchange": false },
    { "name": "Arizona", "abbr": "AZ", "slug": "arizona", "medicaidExpanded": true, "exchange": "Healthcare.gov", "ownExchange": false },
    { "name": "Arkansas", "abbr": "AR", "slug": "arkansas", "medicaidExpanded": true, "exchange": "Healthcare.gov", "ownExchange": false },
    { "name": "California", "abbr": "CA", "slug": "california", "medicaidExpanded": true, "exchange": "Covered California", "ownExchange": true },
    { "name": "Colorado", "abbr": "CO", "slug": "colorado", "medicaidExpanded": true, "exchange": "Connect for Health Colorado", "ownExchange": true },
    { "name": "Connecticut", "abbr": "CT", "slug": "connecticut", "medicaidExpanded": true, "exchange": "Access Health CT", "ownExchange": true },
    { "name": "Delaware", "abbr": "DE", "slug": "delaware", "medicaidExpanded": true, "exchange": "Healthcare.gov", "ownExchange": false },
    { "name": "Florida", "abbr": "FL", "slug": "florida", "medicaidExpanded": false, "exchange": "Healthcare.gov", "ownExchange": false },
    { "name": "Georgia", "abbr": "GA", "slug": "georgia", "medicaidExpanded": false, "exchange": "Healthcare.gov", "ownExchange": false },
    { "name": "Hawaii", "abbr": "HI", "slug": "hawaii", "medicaidExpanded": true, "exchange": "Healthcare.gov", "ownExchange": false },
    { "name": "Idaho", "abbr": "ID", "slug": "idaho", "medicaidExpanded": true, "exchange": "Your Health Idaho", "ownExchange": true },
    { "name": "Illinois", "abbr": "IL", "slug": "illinois", "medicaidExpanded": true, "exchange": "Get Covered Illinois", "ownExchange": true },
    { "name": "Indiana", "abbr": "IN", "slug": "indiana", "medicaidExpanded": true, "exchange": "Healthcare.gov", "ownExchange": false },
    { "name": "Iowa", "abbr": "IA", "slug": "iowa", "medicaidExpanded": true, "exchange": "Healthcare.gov", "ownExchange": false },
    { "name": "Kansas", "abbr": "KS", "slug": "kansas", "medicaidExpanded": false, "exchange": "Healthcare.gov", "ownExchange": false },
    { "name": "Kentucky", "abbr": "KY", "slug": "kentucky", "medicaidExpanded": true, "exchange": "kynect", "ownExchange": true },
    { "name": "Louisiana", "abbr": "LA", "slug": "louisiana", "medicaidExpanded": true, "exchange": "Healthcare.gov", "ownExchange": false },
    { "name": "Maine", "abbr": "ME", "slug": "maine", "medicaidExpanded": true, "exchange": "Healthcare.gov", "ownExchange": false },
    { "name": "Maryland", "abbr": "MD", "slug": "maryland", "medicaidExpanded": true, "exchange": "Maryland Health Connection", "ownExchange": true },
    { "name": "Massachusetts", "abbr": "MA", "slug": "massachusetts", "medicaidExpanded": true, "exchange": "Massachusetts Health Connector", "ownExchange": true },
    { "name": "Michigan", "abbr": "MI", "slug": "michigan", "medicaidExpanded": true, "exchange": "Healthcare.gov", "ownExchange": false },
    { "name": "Minnesota", "abbr": "MN", "slug": "minnesota", "medicaidExpanded": true, "exchange": "MNsure", "ownExchange": true },
    { "name": "Mississippi", "abbr": "MS", "slug": "mississippi", "medicaidExpanded": false, "exchange": "Healthcare.gov", "ownExchange": false },
    { "name": "Missouri", "abbr": "MO", "slug": "missouri", "medicaidExpanded": true, "exchange": "Healthcare.gov", "ownExchange": false },
    { "name": "Montana", "abbr": "MT", "slug": "montana", "medicaidExpanded": true, "exchange": "Healthcare.gov", "ownExchange": false },
    { "name": "Nebraska", "abbr": "NE", "slug": "nebraska", "medicaidExpanded": true, "exchange": "Healthcare.gov", "ownExchange": false },
    { "name": "Nevada", "abbr": "NV", "slug": "nevada", "medicaidExpanded": true, "exchange": "Nevada Health Link", "ownExchange": true },
    { "name": "New Hampshire", "abbr": "NH", "slug": "new-hampshire", "medicaidExpanded": true, "exchange": "Healthcare.gov", "ownExchange": false },
    { "name": "New Jersey", "abbr": "NJ", "slug": "new-jersey", "medicaidExpanded": true, "exchange": "Get Covered New Jersey", "ownExchange": true },
    { "name": "New Mexico", "abbr": "NM", "slug": "new-mexico", "medicaidExpanded": true, "exchange": "beWellnm", "ownExchange": true },
    { "name": "New York", "abbr": "NY", "slug": "new-york", "medicaidExpanded": true, "exchange": "NY State of Health", "ownExchange": true },
    { "name": "North Carolina", "abbr": "NC", "slug": "north-carolina", "medicaidExpanded": true, "exchange": "Healthcare.gov", "ownExchange": false },
    { "name": "North Dakota", "abbr": "ND", "slug": "north-dakota", "medicaidExpanded": true, "exchange": "Healthcare.gov", "ownExchange": false },
    { "name": "Ohio", "abbr": "OH", "slug": "ohio", "medicaidExpanded": true, "exchange": "Healthcare.gov", "ownExchange": false },
    { "name": "Oklahoma", "abbr": "OK", "slug": "oklahoma", "medicaidExpanded": true, "exchange": "Healthcare.gov", "ownExchange": false },
    { "name": "Oregon", "abbr": "OR", "slug": "oregon", "medicaidExpanded": true, "exchange": "Oregon Health Insurance Marketplace", "ownExchange": true },
    { "name": "Pennsylvania", "abbr": "PA", "slug": "pennsylvania", "medicaidExpanded": true, "exchange": "Pennie", "ownExchange": true },
    { "name": "Rhode Island", "abbr": "RI", "slug": "rhode-island", "medicaidExpanded": true, "exchange": "HealthSource RI", "ownExchange": true },
    { "name": "South Carolina", "abbr": "SC", "slug": "south-carolina", "medicaidExpanded": false, "exchange": "Healthcare.gov", "ownExchange": false },
    { "name": "South Dakota", "abbr": "SD", "slug": "south-dakota", "medicaidExpanded": true, "exchange": "Healthcare.gov", "ownExchange": false },
    { "name": "Tennessee", "abbr": "TN", "slug": "tennessee", "medicaidExpanded": false, "exchange": "Healthcare.gov", "ownExchange": false },
    { "name": "Texas", "abbr": "TX", "slug": "texas", "medicaidExpanded": false, "exchange": "Healthcare.gov", "ownExchange": false },
    { "name": "Utah", "abbr": "UT", "slug": "utah", "medicaidExpanded": true, "exchange": "Healthcare.gov", "ownExchange": false },
    { "name": "Vermont", "abbr": "VT", "slug": "vermont", "medicaidExpanded": true, "exchange": "Vermont Health Connect", "ownExchange": true },
    { "name": "Virginia", "abbr": "VA", "slug": "virginia", "medicaidExpanded": true, "exchange": "Healthcare.gov", "ownExchange": false },
    { "name": "Washington", "abbr": "WA", "slug": "washington", "medicaidExpanded": true, "exchange": "Washington Healthplanfinder", "ownExchange": true },
    { "name": "West Virginia", "abbr": "WV", "slug": "west-virginia", "medicaidExpanded": true, "exchange": "Healthcare.gov", "ownExchange": false },
    { "name": "Wisconsin", "abbr": "WI", "slug": "wisconsin", "medicaidExpanded": false, "exchange": "Healthcare.gov", "ownExchange": false },
    { "name": "Wyoming", "abbr": "WY", "slug": "wyoming", "medicaidExpanded": false, "exchange": "Healthcare.gov", "ownExchange": false },
    { "name": "District of Columbia", "abbr": "DC", "slug": "district-of-columbia", "medicaidExpanded": true, "exchange": "DC Health Link", "ownExchange": true }
  ]
}
